arty/__init__.py
arty/core/__init__.py
arty/core/brush.py
arty/core/color.py
arty/core/angle/__init__.py
arty/core/angle/_conditional.py
arty/core/angle/_gradient_based.py
arty/core/angle/_cnn/__init__.py
arty/core/angle/_cnn/_generate.py
arty/core/angle/_cnn/_train.py
arty/core/angle/cnn/__init__.py
arty/core/angle/cnn/_generate.py
arty/core/angle/cnn/_train.py
arty/core/edge/__init__.py
arty/core/edge/gradient.py
arty/core/filter/__init__.py
arty/core/filter/_lines.py
arty/core/filter/_noise.py
arty/core/filter/_points.py
arty/core/filter/_strokes.py
arty/core/filter/color.py
arty/core/filter/blur/__init__.py
arty/core/filter/blur/_gauss.py
arty/filter/__init__.py
arty/filter/_lines.py
arty/filter/_pencil.py
arty/filter/_points.py
arty/filter/_strokes.py
arty/nn/__init__.py
arty/nn/cnn.py
arty/sbr/__init__.py
arty/sbr/image_painter.py
arty/sbr/preset.py
artypy-0.14.0.dist-info/METADATA
artypy-0.14.0.dist-info/WHEEL
artypy-0.14.0.dist-info/top_level.txt
artypy-0.14.0.dist-info/RECORD
