Metadata-Version: 2.1
Name: artypy
Version: 0.14.0
Summary: Lightweight library for artistic filters
Home-page: https://github.com/artypy/arty
Author: artypy team
Author-email: ahmatovbulat@gmail.com
Classifier: Programming Language :: Python :: 3
Classifier: License :: OSI Approved :: MIT License
Classifier: Operating System :: OS Independent
Requires-Python: >=3.11
Requires-Dist: numpy
Requires-Dist: matplotlib
Requires-Dist: tqdm
Requires-Dist: opencv-python
Requires-Dist: progressbar
Requires-Dist: scipy
Requires-Dist: scikit-learn
Provides-Extra: cuda
Requires-Dist: torch ; extra == 'cuda'
